insta360_lib/__init__.py
insta360_lib/_dll_wrapper.py
insta360_lib/dlls/MSVCP140D.dll
insta360_lib/dlls/VCRUNTIME140D.dll
insta360_lib/dlls/VCRUNTIME140_1D.dll
insta360_lib/dlls/mfc100.dll
insta360_lib/dlls/msvcp100.dll
insta360_lib/dlls/msvcp120.dll
insta360_lib/dlls/msvcr100.dll
insta360_lib/dlls/msvcr120.dll
insta360_lib/dlls/ucrtbased.dll
insta360_lib/dlls/vcomp100.dll
insta360_lib/dlls/vcomp120.dll
insta360_lib/dlls/VB/CommonAlgorithmSFR.dll
insta360_lib/dlls/VB/GetROIInfo.dll
insta360_lib/dlls/VB/ImgTestAlg.dll
insta360_lib/dlls/VB/LED_Analyzer.dll
insta360_lib/dlls/VB/SFR_LENOVO.dll
insta360_lib/dlls/VB/StrayLightDetectAlg.dll
insta360_lib/dlls/VB/SunnyInsta_puc2.dll
insta360_lib/dlls/VB/SunnyUnifySFRAlgorithmDLL.dll
insta360_lib/dlls/VB/ToolLib.dll
insta360_lib/dlls/VB/VBJN1SFRTEST.dll
insta360_lib/dlls/VB/libraw.dll
insta360_lib/dlls/VB/opencv_core2410.dll
insta360_lib/dlls/VB/opencv_highgui2410.dll
insta360_lib/dlls/VB/opencv_imgproc2410.dll
insta360_lib/dlls/VB/puc2Sfr.dll
insta360_lib/dlls/VB/puc3Sfr.dll
insta360_lib/dlls/VB/sunnyInstaSFR.dll
insta360_lib/dlls/VB/vbSfr.dll
insta360_lib/dlls/iac3/IacSfr.dll
insta360_lib/dlls/iac3/StrayLightDetectAlg.dll
insta360_lib/dlls/iac3/opencv_core2410.dll
insta360_lib/dlls/iac3/opencv_highgui2410.dll
insta360_lib/dlls/iac3/opencv_imgproc2410.dll
insta360_lib/dlls/iac3/sunnyInstaSFR.dll
insta360_lib-0.2.5.dist-info/METADATA
insta360_lib-0.2.5.dist-info/WHEEL
insta360_lib-0.2.5.dist-info/top_level.txt
insta360_lib-0.2.5.dist-info/RECORD
